CHANGELOG.txt
LICENCE.txt
MANIFEST.in
README.md
README.txt
setup.py
test.py
.eggs/README.txt
.eggs/setuptools-46.0.0-py3.7.egg/easy_install.py
.eggs/setuptools-46.0.0-py3.7.egg/EGG-INFO/dependency_links.txt
.eggs/setuptools-46.0.0-py3.7.egg/EGG-INFO/entry_points.txt
.eggs/setuptools-46.0.0-py3.7.egg/EGG-INFO/top_level.txt
.eggs/setuptools-46.0.0-py3.7.egg/pkg_resources/__init__.py
.eggs/setuptools-46.0.0-py3.7.egg/pkg_resources/py2_warn.py
.eggs/setuptools-46.0.0-py3.7.egg/pkg_resources/py31compat.py
.eggs/setuptools-46.0.0-py3.7.egg/pkg_resources/_vendor/__init__.py
.eggs/setuptools-46.0.0-py3.7.egg/pkg_resources/_vendor/appdirs.py
.eggs/setuptools-46.0.0-py3.7.egg/pkg_resources/_vendor/pyparsing.py
.eggs/setuptools-46.0.0-py3.7.egg/pkg_resources/_vendor/six.py
.eggs/setuptools-46.0.0-py3.7.egg/pkg_resources/_vendor/packaging/__about__.py
.eggs/setuptools-46.0.0-py3.7.egg/pkg_resources/_vendor/packaging/__init__.py
.eggs/setuptools-46.0.0-py3.7.egg/pkg_resources/_vendor/packaging/_compat.py
.eggs/setuptools-46.0.0-py3.7.egg/pkg_resources/_vendor/packaging/_structures.py
.eggs/setuptools-46.0.0-py3.7.egg/pkg_resources/_vendor/packaging/markers.py
.eggs/setuptools-46.0.0-py3.7.egg/pkg_resources/_vendor/packaging/requirements.py
.eggs/setuptools-46.0.0-py3.7.egg/pkg_resources/_vendor/packaging/specifiers.py
.eggs/setuptools-46.0.0-py3.7.egg/pkg_resources/_vendor/packaging/utils.py
.eggs/setuptools-46.0.0-py3.7.egg/pkg_resources/_vendor/packaging/version.py
.eggs/setuptools-46.0.0-py3.7.egg/pkg_resources/extern/__init__.py
.eggs/setuptools-46.0.0-py3.7.egg/setuptools/__init__.py
.eggs/setuptools-46.0.0-py3.7.egg/setuptools/_deprecation_warning.py
.eggs/setuptools-46.0.0-py3.7.egg/setuptools/_imp.py
.eggs/setuptools-46.0.0-py3.7.egg/setuptools/archive_util.py
.eggs/setuptools-46.0.0-py3.7.egg/setuptools/build_meta.py
.eggs/setuptools-46.0.0-py3.7.egg/setuptools/config.py
.eggs/setuptools-46.0.0-py3.7.egg/setuptools/dep_util.py
.eggs/setuptools-46.0.0-py3.7.egg/setuptools/depends.py
.eggs/setuptools-46.0.0-py3.7.egg/setuptools/dist.py
.eggs/setuptools-46.0.0-py3.7.egg/setuptools/errors.py
.eggs/setuptools-46.0.0-py3.7.egg/setuptools/extension.py
convert_numbers.egg-info/PKG-INFO
convert_numbers.egg-info/SOURCES.txt
convert_numbers.egg-info/dependency_links.txt
convert_numbers.egg-info/top_level.txt