Metadata-Version: 2.1
Name: convert-numbers
Version: 0.0.3
Summary: Arabic Persian English Hindi Numbers is a Python library to convert numbers from-to Arabic, Hinid, Persian and English.
Home-page: https://github.com/azwri/convert_numbers
Author: Azwri
Author-email: aazwri@gmail.com
License: MIT
Keywords: Arabic Persian English Hindi Numbers Python conversion numbers from-to Arabic,Hinid,Persian and English
Platform: UNKNOWN
Classifier: Development Status :: 5 - Production/Stable
Classifier: Operating System :: OS Independent
Classifier: License :: OSI Approved :: MIT License
Classifier: Programming Language :: Python :: 3
